bookable_event_logger/__init__.py
bookable_event_logger/logger.py
bookable_event_logger-0.2.0.dist-info/METADATA
bookable_event_logger-0.2.0.dist-info/WHEEL
bookable_event_logger-0.2.0.dist-info/top_level.txt
bookable_event_logger-0.2.0.dist-info/RECORD
