Metadata-Version: 2.4
Name: bookable-event-logger
Version: 0.2.0
Summary: Internal Pub/Sub → BigQuery event logger for Bookable services (Python)
Author-email: Pat <pat@bookabletech.com>
License: MIT
Project-URL: Homepage, https://github.com/yourusername/bookable-event-logger
Project-URL: Bug Tracker, https://github.com/yourusername/bookable-event-logger/issues
Classifier: Programming Language :: Python :: 3
Classifier: Programming Language :: Python :: 3.10
Classifier: Programming Language :: Python :: 3.11
Classifier: Programming Language :: Python :: 3.12
Classifier: License :: OSI Approved :: MIT License
Classifier: Operating System :: OS Independent
Requires-Python: >=3.10
Requires-Dist: google-cloud-pubsub>=2.21.0
Requires-Dist: google-auth>=2.0.0
